{
  "formCan": [
    {
      "id": "96c8",
      "name": "Phụng Nguyễn",
      "email": "minhphungbmt141999@gmail.com",
      "phone": "0942124828",
      "note": "edafvfsdvsdvsd"
    },
    {
      "id": "0b4d",
      "name": "Phụng Nguyễn",
      "email": "minhphungbmt141999@gmail.com",
      "phone": "0942124828",
      "note": ""
    },
    {
      "id": "7f61",
      "name": "Phụng Nguyễn",
      "email": "minhphungbmt141999@gmail.com",
      "phone": "0942124828",
      "note": ""
    }
  ]
}